CaptchaLibrary/CaptchaLibrary.py
CaptchaLibrary/__init__.py
CaptchaLibrary/version.py
CaptchaLibrary/services/__init__.py
CaptchaLibrary/services/forgotcaptcha/ForgotCaptcha.py
CaptchaLibrary/services/forgotcaptcha/__init__.py
CaptchaLibrary/services/twocaptcha/SimpleCaptcha.py
CaptchaLibrary/services/twocaptcha/__init__.py
CaptchaLibrary/utils/Configuration.py
CaptchaLibrary/utils/EncDec.py
CaptchaLibrary/utils/Img.py
CaptchaLibrary/utils/__init__.py
robotframework_captchalibrary-1.0a3.dist-info/LICENSE
robotframework_captchalibrary-1.0a3.dist-info/METADATA
robotframework_captchalibrary-1.0a3.dist-info/WHEEL
robotframework_captchalibrary-1.0a3.dist-info/top_level.txt
robotframework_captchalibrary-1.0a3.dist-info/RECORD
